{"name_i18n":{"es-ES":"Solicitud de Excedencias - Tipos"},"name":"Solicitud de Excedencias - Tipos","listTypeEntries":[{"name_i18n":{"es-ES":"Excedencia por cuidado de familiares/ forzosa"},"name":"Excedencia por cuidado de familiares/ forzosa","type":"","key":"excedenciCuidadoFamiliares","externalReferenceCode":"f99a0c8e-4027-ff6a-6595-eb1d6af7ee6a"},{"name_i18n":{"es-ES":"Exedencia voluntaria"},"name":"Exedencia voluntaria","type":"","key":"exedenciaVoluntaria","externalReferenceCode":"87ab33aa-9029-5969-9e28-9cc636d484d8"}],"externalReferenceCode":"bd5558b7-8a54-823c-392f-423355fe6940"}